openapi_client/__init__.py
openapi_client/api_client.py
openapi_client/api_response.py
openapi_client/configuration.py
openapi_client/exceptions.py
openapi_client/py.typed
openapi_client/rest.py
openapi_client/api/__init__.py
openapi_client/api/catalog_api.py
openapi_client/api/jobs_api.py
openapi_client/api/proof_api.py
openapi_client/api/utilities_api.py
openapi_client/api/version_api.py
openapi_client/models/__init__.py
openapi_client/models/alternate_response_data_wrapper.py
openapi_client/models/alternate_response_data_wrapper1.py
openapi_client/models/alternate_response_data_wrapper1_data.py
openapi_client/models/alternate_response_data_wrapper1_data_jobs_inner.py
openapi_client/models/alternate_response_data_wrapper2.py
openapi_client/models/alternate_response_data_wrapper2_data.py
openapi_client/models/alternate_response_data_wrapper3.py
openapi_client/models/alternate_response_data_wrapper3_anchors_inner.py
openapi_client/models/alternate_response_data_wrapper3_verification.py
openapi_client/models/alternate_response_data_wrapper_data.py
openapi_client/models/alternate_response_data_wrapper_data_jobs_inner.py
openapi_client/models/alternate_response_data_wrapper_data_pending_version.py
openapi_client/models/alternate_response_extended_anchor_metadata.py
openapi_client/models/alternate_response_extended_anchor_metadata_anchors_inner.py
openapi_client/models/alternate_response_extended_anchor_metadata_verification.py
openapi_client/models/bytesbase64.py
openapi_client/models/bytesbase641.py
openapi_client/models/bytesbase642.py
openapi_client/models/catalog_catalog_id_proof_get200_response.py
openapi_client/models/catalog_catalog_id_proof_get200_response_data.py
openapi_client/models/catalog_catalog_id_proof_get200_response_data_version.py
openapi_client/models/catalog_catalog_id_proof_get200_response_data_version_anchors_inner.py
openapi_client/models/catalog_catalog_id_proof_get200_response_data_version_verification.py
rekord_io_sdk-1.0.4.dist-info/METADATA
rekord_io_sdk-1.0.4.dist-info/WHEEL
rekord_io_sdk-1.0.4.dist-info/top_level.txt
rekord_io_sdk-1.0.4.dist-info/RECORD
