Metadata-Version: 2.4
Name: rekord-io-sdk
Version: 1.0.4
Summary: Rekord.io SDK
Home-page: 
Author: OpenAPI Generator community
Author-email: "Rekord.io" <kulkvibh@rekord.io>
Project-URL: Repository, https://github.com/Rekord-io/trust-layer
Keywords: Rekord.io,SDK
Requires-Python: >=3.9
Requires-Dist: urllib3<3.0.0,>=2.1.0
Requires-Dist: python-dateutil>=2.8.2
Requires-Dist: pydantic>=2
Requires-Dist: typing-extensions>=4.7.1
Dynamic: author
